pytopomap/__init__.py
pytopomap/plot.py
pytopomap/plot_3d.py
pytopomap/tools.py
pytopomap-0.0.3.dist-info/licenses/LICENSE
pytopomap-0.0.3.dist-info/METADATA
pytopomap-0.0.3.dist-info/WHEEL
pytopomap-0.0.3.dist-info/top_level.txt
pytopomap-0.0.3.dist-info/RECORD
