Metadata-Version: 2.4
Name: pytopomap
Version: 0.0.3
Summary: Topographic visualization tools
Author-email: Marc Peruzzetto <m.peruzzetto@brgm.fr>
License-Expression: LGPL-2.1-or-later
Project-URL: Homepage, https://github.com/marcperuz/pytopomap
Keywords: topography,display
Classifier: Programming Language :: Python
Classifier: Programming Language :: Python :: 3
Requires-Python: >=3.10
License-File: LICENSE
Requires-Dist: plotly
Provides-Extra: test
Requires-Dist: pytest; extra == "test"
Provides-Extra: dev
Requires-Dist: pipreqs; extra == "dev"
Provides-Extra: gis
Requires-Dist: rasterio; extra == "gis"
Dynamic: license-file
